UselessConsole/Console.py
UselessConsole/__init__.py
uselessconsole-0.1.3.dist-info/METADATA
uselessconsole-0.1.3.dist-info/WHEEL
uselessconsole-0.1.3.dist-info/licenses/LICENSE
uselessconsole-0.1.3.dist-info/RECORD
