Metadata-Version: 2.1
Name: UselessConsole
Version: 0.1.3
Summary: Console package that has the ability to print and replace console output. That's literally it, this package is useless.
Project-URL: Homepage, https://google.com/
Project-URL: Bug Tracker, https://google.com/
Author-email: Alternate <alternated@mooncorerbx.com>
License-File: LICENSE
Classifier: License :: OSI Approved :: MIT License
Classifier: Operating System :: OS Independent
Classifier: Programming Language :: Python :: 3
Requires-Python: >=3.7
